sender_policy_flattener/__init__.py
sender_policy_flattener/cli.py
sender_policy_flattener/crawler.py
sender_policy_flattener/email_utils.py
sender_policy_flattener/formatting.py
sender_policy_flattener/handlers.py
sender_policy_flattener/mechanisms.py
sender_policy_flattener-0.4.0.dist-info/METADATA
sender_policy_flattener-0.4.0.dist-info/WHEEL
sender_policy_flattener-0.4.0.dist-info/entry_points.txt
sender_policy_flattener-0.4.0.dist-info/licenses/LICENSE
sender_policy_flattener-0.4.0.dist-info/RECORD
