Metadata-Version: 2.4
Name: sender_policy_flattener
Version: 0.4.0
Summary: Condense SPF records to network blocks to avoid DNS Lookup Limits
Project-URL: Repository, https://github.com/cetanu/sender_policy_flattener
Author-email: Vasili Syrakis <cetanu@gmail.com>
License-Expression: MIT
License-File: LICENSE
Keywords: dns,sender policy framework,spf
Classifier: Development Status :: 5 - Production/Stable
Classifier: Intended Audience :: System Administrators
Classifier: License :: OSI Approved :: MIT License
Classifier: Natural Language :: English
Classifier: Programming Language :: Python :: 2.7
Classifier: Programming Language :: Python :: 3.3
Classifier: Programming Language :: Python :: 3.4
Classifier: Programming Language :: Python :: 3.5
Classifier: Programming Language :: Python :: 3.6
Classifier: Programming Language :: Python :: Implementation :: CPython
Classifier: Topic :: Internet :: Name Service (DNS)
Classifier: Topic :: System :: Systems Administration
Classifier: Topic :: Utilities
Requires-Python: <4,>=3.10.0
Requires-Dist: dnspython
Requires-Dist: netaddr
